llmInvoker/__init__.py
llmInvoker/config.py
llmInvoker/core.py
llmInvoker/history.py
llmInvoker/providers.py
llmInvoker/strategies.py
llmInvoker/utils.py
llm_invoker-0.1.3.dist-info/METADATA
llm_invoker-0.1.3.dist-info/WHEEL
llm_invoker-0.1.3.dist-info/licenses/LICENSE
llm_invoker-0.1.3.dist-info/RECORD
