Metadata-Version: 2.4
Name: llm-invoker
Version: 0.1.3
Summary: A Python library for managing multi-agent model invocation with automatic failover strategies
Project-URL: Homepage, https://github.com/JlassiRAed/llm-invoker
Project-URL: Repository, https://github.com/JlassiRAed/llm-invoker
Project-URL: Documentation, https://github.com/JlassiRAed/llm-invoker/#readme
Project-URL: Issues, https://github.com/JlassiRAed/llm-invoker/issues
Author-email: Jlassi Raed <raed.jlassi@etudiant-enit.utm.tn>
License: MIT
License-File: LICENSE
Keywords: ai,anthropic,failover,github,google,llm,multiagent,openai
Classifier: Development Status :: 3 - Alpha
Classifier: Intended Audience :: Developers
Classifier: License :: OSI Approved :: MIT License
Classifier: Programming Language :: Python :: 3
Classifier: Programming Language :: Python :: 3.9
Classifier: Programming Language :: Python :: 3.10
Classifier: Programming Language :: Python :: 3.11
Classifier: Programming Language :: Python :: 3.12
Classifier: Topic :: Scientific/Engineering :: Artificial Intelligence
Classifier: Topic :: Software Development :: Libraries :: Python Modules
Requires-Python: >=3.9
Requires-Dist: aiohttp>=3.8.0
Requires-Dist: anthropic>=0.25.0
Requires-Dist: asyncio-throttle>=1.0.0
Requires-Dist: google-generativeai>=0.3.0
Requires-Dist: langchain>=0.1.0
Requires-Dist: langsmith>=0.1.0
Requires-Dist: openai>=1.0.0
Requires-Dist: python-dotenv>=0.19.1
Requires-Dist: requests>=2.25.1
Requires-Dist: setuptools>=80.9.0
Requires-Dist: twine>=6.1.0
Requires-Dist: typing-extensions>=4.0.0
Provides-Extra: dev
Requires-Dist: black>=23.0.0; extra == 'dev'
Requires-Dist: flake8>=6.0.0; extra == 'dev'
Requires-Dist: mypy>=1.0.0; extra == 'dev'
Requires-Dist: pytest-asyncio>=0.21.0; extra == 'dev'
Requires-Dist: pytest-cov>=4.0.0; extra == 'dev'
Requires-Dist: pytest-mock>=3.10.0; extra == 'dev'
Requires-Dist: pytest>=7.0.0; extra == 'dev'
